src/topsis.py
Topsis_gurnoor_102003069-0.1.0.dist-info/METADATA
Topsis_gurnoor_102003069-0.1.0.dist-info/WHEEL
Topsis_gurnoor_102003069-0.1.0.dist-info/entry_points.txt
Topsis_gurnoor_102003069-0.1.0.dist-info/top_level.txt
Topsis_gurnoor_102003069-0.1.0.dist-info/RECORD
